powerschoollearning/__init__.py
powerschoollearning/assignments.py
powerschoollearning/classes.py
powerschoollearning/errors.py
powerschoollearning/grades.py
powerschoollearning-1.0.1.dist-info/LICENSE
powerschoollearning-1.0.1.dist-info/METADATA
powerschoollearning-1.0.1.dist-info/WHEEL
powerschoollearning-1.0.1.dist-info/top_level.txt
powerschoollearning-1.0.1.dist-info/RECORD
