Metadata-Version: 2.1
Name: powerschoollearning
Version: 1.0.1
Summary: Python library for powerschool learning.
Home-page: https://github.com/gubareve/powerschool-learning-api
Author: gubareve
License: LICENSE
Platform: UNKNOWN
Requires-Dist: aiohttp
